{
    "id":"Kaggle::techmap::612f493d74360e55efe19616::monsterasia_in::14",
    "label_age":false,
    "analysis_age":null,
    "label_disability":false,
    "analysis_disability":null,
    "label_masculine":false,
    "analysis_masculine":null,
    "label_feminine":false,
    "analysis_feminine":null,
    "label_racial":false,
    "analysis_racial":null,
    "label_sexuality":false,
    "analysis_sexuality":null,
    "label_general":false,
    "analysis_general":null,
    "verified":true,
    "synthetic":false,
    "text":"Job Title. Cluster Head - CASA. Place of work. Mumbai. Business Unit. Retail Banking. Function -Branch Banking. Job Purpose : The role entails overseeing the operational aspects of branches including distribution operations, customer service, administration and sales. The role bearer is responsible for guiding the Branch Managers in assessing local market conditions and identifying current and prospective sales opportunities. The role bearer must develop forecasts, financial objectives and business plans contributing to the larger branch banking channel objectives. Roles & Responsibilities: Manage budget and allocate funds appropriately. Locate areas of improvement and propose corrective actions that meet challenges and leverage growth opportunities. Share knowledge with other branches and headquarters on effective practices, competitive intelligence, business opportunities and needs. Address customer and employee satisfaction issues promptly. Adhere to high ethical standards, and comply with all regulations\/applicable laws. Network to improve the presence and reputation of the branch and company. Stay abreast of competing markets and provide reports on market movement and penetration. Establish the Bank and the brand in the catchment area. Responsible for achieving overall product targets for the Cluster - CASA, Investments, Insurance, Trade Services, and TD & managing group business products like Business Banking products & other assets products (home loan, LAP etc. ). Cultivate relationships with individual and corporate customers. Managing customer centric operations & ensuring customer satisfaction by achieving delivery & service quality norms. Evaluate the growth strategy based on competitor analysis and feedback from different channels\/customers. Recommend process changes in order to improve service efficiency and quality across the branch network. Monitor the branch network expansion as per the defined business plan. Managerial & Leadership Responsibilities: Attract and retain best-in-class talent for key roles in their reporting structure. Monitor key parameters on employee productivity, hiring quality and attrition rates and make necessary improvements. Enable teams to drive growth targets by providing necessary support. Educational Qualifications: Graduate \u00e2\u20ac\" Any. Post Graduate. Finance (MBA preferred). Experience: 15. years of relevant branch banking experience",
    "metadata":"{\"document_id\": \"Kaggle::techmap::612f493d74360e55efe19616::monsterasia_in\", \"source\": \"monsterasia_in\", \"country\": \"IN\", \"company\": \"IDFC FIRST Bank\", \"position\": \"Cluster Head\", \"notes\": \"\", \"original\": \"<br><strong>Job Title -<\/strong> Cluster Head - CASA<br><strong>Place of work<\/strong> - Mumbai<br><strong>Business Unit<\/strong> - Retail Banking<br><strong>Function<\/strong> -Branch Banking<br><strong>Job Purpose :<\/strong><br>The role entails overseeing the operational aspects of branches including distribution operations, customer service, administration and sales. The role bearer is responsible for guiding the Branch Managers in assessing local market conditions and identifying current and prospective sales opportunities. The role bearer must develop forecasts, financial objectives and business plans contributing to the larger branch banking channel objectives.<br><strong>Roles & Responsibilities: <\/strong><ul><li>Manage budget and allocate funds appropriately<\/li><li>Locate areas of improvement and propose corrective actions that meet challenges and leverage growth opportunities.<\/li><li>Share knowledge with other branches and headquarters on effective practices, competitive intelligence, business opportunities and needs.<\/li><li>Address customer and employee satisfaction issues promptly.<\/li><li>Adhere to high ethical standards, and comply with all regulations\/applicable laws<\/li><li>Network to improve the presence and reputation of the branch and company<\/li><li>Stay abreast of competing markets and provide reports on market movement and penetration<\/li><li>Establish the Bank and the brand in the catchment area<\/li><li>Responsible for achieving overall product targets for the Cluster - CASA, Investments, Insurance, Trade Services, and TD & managing group business products like Business Banking products & other assets products (home loan, LAP etc.)<\/li><li>Cultivate relationships with individual and corporate customers<\/li><li>Managing customer centric operations & ensuring customer satisfaction by achieving delivery & service quality norms<\/li><li>Evaluate the growth strategy based on competitor analysis and feedback from different channels\/customers<\/li><li>Recommend process changes in order to improve service efficiency and quality across the branch network<\/li><li>Facilitate a customer centric branch channel and achieve\/exceed the defined NPS targets<\/li><li>Monitor the branch network expansion as per the defined business plan<\/li><\/ul><br><strong>Managerial & Leadership Responsibilities: <\/strong><ul><li>Attract and retain best-in-class talent for key roles in their reporting structure<\/li><li>Monitor key parameters on employee productivity, hiring quality and attrition rates and make necessary improvements<\/li><li>Enable teams to drive growth targets by providing necessary support<\/li><\/ul><br><strong>Educational Qualifications: <\/strong><br>Graduate \\u00e2\\u20ac\\\" Any<br>Post Graduate - Finance (MBA preferred)<br><strong>Experience:<\/strong><br>15+ years of relevant branch banking experience\"}"
}